[
	{
		"name": "MC (Mikrocontrollersysteme)",
		"location": "10.65, Berliner Tor 7",
		"description": "Dozent: Prof. Dr.-Ing. Karl-Ragmar Riemschneider\nMax. Anzahl von Teilnehmer/-innen: 24\nRhythmus: wöchentlich\n\nOriginaler Titel: MC",
		"startTime": "2025-10-07T15:55:00",
		"endTime": "2025-10-07T19:10:00"
	},
	{
		"name": "MC (Mikrocontrollersysteme)",
		"location": "10.65, Berliner Tor 7",
		"description": "Dozent: Prof. Dr.-Ing. Karl-Ragmar Riemschneider\nMax. Anzahl von Teilnehmer/-innen: 24\nRhythmus: wöchentlich\n\nOriginaler Titel: MC",
		"startTime": "2025-10-14T15:55:00",
		"endTime": "2025-10-14T19:10:00"
	},
	{
		"name": "MC (Mikrocontrollersysteme)",
		"location": "10.65, Berliner Tor 7",
		"description": "Dozent: Prof. Dr.-Ing. Karl-Ragmar Riemschneider\nMax. Anzahl von Teilnehmer/-innen: 24\nRhythmus: wöchentlich\n\nOriginaler Titel: MC",
		"startTime": "2025-10-21T15:55:00",
		"endTime": "2025-10-21T19:10:00"
	},
	{
		"name": "MC (Mikrocontrollersysteme)",
		"location": "10.65, Berliner Tor 7",
		"description": "Dozent: Prof. Dr.-Ing. Karl-Ragmar Riemschneider\nMax. Anzahl von Teilnehmer/-innen: 24\nRhythmus: wöchentlich\n\nOriginaler Titel: MC",
		"startTime": "2025-10-28T15:55:00",
		"endTime": "2025-10-28T19:10:00"
	},
	{
		"name": "MC (Mikrocontrollersysteme)",
		"location": "10.65, Berliner Tor 7",
		"description": "Dozent: Prof. Dr.-Ing. Karl-Ragmar Riemschneider\nMax. Anzahl von Teilnehmer/-innen: 24\nRhythmus: wöchentlich\n\nOriginaler Titel: MC",
		"startTime": "2025-11-11T15:55:00",
		"endTime": "2025-11-11T19:10:00"
	},
	{
		"name": "MC (Mikrocontrollersysteme)",
		"location": "10.65, Berliner Tor 7",
		"description": "Dozent: Prof. Dr.-Ing. Karl-Ragmar Riemschneider\nMax. Anzahl von Teilnehmer/-innen: 24\nRhythmus: wöchentlich\n\nOriginaler Titel: MC",
		"startTime": "2025-11-18T15:55:00",
		"endTime": "2025-11-18T19:10:00"
	},
	{
		"name": "MC (Mikrocontrollersysteme)",
		"location": "10.65, Berliner Tor 7",
		"description": "Dozent: Prof. Dr.-Ing. Karl-Ragmar Riemschneider\nMax. Anzahl von Teilnehmer/-innen: 24\nRhythmus: wöchentlich\n\nOriginaler Titel: MC",
		"startTime": "2025-11-25T15:55:00",
		"endTime": "2025-11-25T19:10:00"
	},
	{
		"name": "MC (Mikrocontrollersysteme)",
		"location": "10.65, Berliner Tor 7",
		"description": "Dozent: Prof. Dr.-Ing. Karl-Ragmar Riemschneider\nMax. Anzahl von Teilnehmer/-innen: 24\nRhythmus: wöchentlich\n\nOriginaler Titel: MC",
		"startTime": "2025-12-02T15:55:00",
		"endTime": "2025-12-02T19:10:00"
	},
	{
		"name": "MC (Mikrocontrollersysteme)",
		"location": "10.65, Berliner Tor 7",
		"description": "Dozent: Prof. Dr.-Ing. Karl-Ragmar Riemschneider\nMax. Anzahl von Teilnehmer/-innen: 24\nRhythmus: wöchentlich\n\nOriginaler Titel: MC",
		"startTime": "2025-12-09T15:55:00",
		"endTime": "2025-12-09T19:10:00"
	},
	{
		"name": "MC (Mikrocontrollersysteme)",
		"location": "10.65, Berliner Tor 7",
		"description": "Dozent: Prof. Dr.-Ing. Karl-Ragmar Riemschneider\nMax. Anzahl von Teilnehmer/-innen: 24\nRhythmus: wöchentlich\n\nOriginaler Titel: MC",
		"startTime": "2025-12-16T15:55:00",
		"endTime": "2025-12-16T19:10:00"
	},
	{
		"name": "MC (Mikrocontrollersysteme)",
		"location": "10.65, Berliner Tor 7",
		"description": "Dozent: Prof. Dr.-Ing. Karl-Ragmar Riemschneider\nMax. Anzahl von Teilnehmer/-innen: 24\nRhythmus: Einzeltermin\n\nOriginaler Titel: MC",
		"startTime": "2026-01-06T15:55:00",
		"endTime": "2026-01-06T19:10:00"
	}
]