[
	{
		"name": "BWI1-GM",
		"location": "1001",
		"description": "Dozent: PDB",
		"start": "2024-10-14T14:00:00",
		"end": "2024-10-14T17:15:00"
	},
	{
		"name": "BWI1-GM",
		"location": "1001",
		"description": "Dozent: PDB",
		"start": "2024-10-21T14:00:00",
		"end": "2024-10-21T17:15:00"
	},
	{
		"name": "BWI1-GM",
		"location": "1001",
		"description": "Dozent: PDB",
		"start": "2024-10-28T14:00:00",
		"end": "2024-10-28T17:15:00"
	},
	{
		"name": "BWI1-GM",
		"location": "1001",
		"description": "Dozent: PDB",
		"start": "2024-11-04T14:00:00",
		"end": "2024-11-04T17:15:00"
	},
	{
		"name": "BWI1-GM",
		"location": "1001",
		"description": "Dozent: PDB",
		"start": "2024-11-25T14:00:00",
		"end": "2024-11-25T17:15:00"
	},
	{
		"name": "BWI1-GM",
		"location": "1001",
		"description": "Dozent: PDB",
		"start": "2024-12-16T14:00:00",
		"end": "2024-12-16T17:15:00"
	},
	{
		"name": "BWI1-GM",
		"location": "1001",
		"description": "Dozent: PDB",
		"start": "2025-01-20T14:00:00",
		"end": "2025-01-20T17:15:00"
	},
	{
		"name": "BWI1-GM",
		"location": "1001",
		"description": "Dozent: PDB",
		"start": "2024-11-18T14:00:00",
		"end": "2024-11-18T17:15:00"
	},
	{
		"name": "BWI1-GM",
		"location": "1001",
		"description": "Dozent: PDB",
		"start": "2024-12-09T14:00:00",
		"end": "2024-12-09T17:15:00"
	},
	{
		"name": "BWI1-GM",
		"location": "1001",
		"description": "Dozent: PDB",
		"start": "2025-01-13T14:00:00",
		"end": "2025-01-13T17:15:00"
	},
	{
		"name": "BWI1-GM",
		"location": "1001",
		"description": "Dozent: PDB",
		"start": "2024-12-02T14:00:00",
		"end": "2024-12-02T17:15:00"
	},
	{
		"name": "BWI1-GM",
		"location": "1001",
		"description": "Dozent: PDB",
		"start": "2025-01-06T14:00:00",
		"end": "2025-01-06T17:15:00"
	}
]
