[
	{
		"name": "BWI3-SEAP1/01",
		"location": "1102",
		"description": "Dozent: STF/[Dal]",
		"start": "2024-10-22T08:15:00",
		"end": "2024-10-22T11:30:00"
	},
	{
		"name": "BWI3-SEAP1/01",
		"location": "1102",
		"description": "Dozent: STF/[Dal]",
		"start": "2024-11-12T08:15:00",
		"end": "2024-11-12T11:30:00"
	},
	{
		"name": "BWI3-SEAP1/01",
		"location": "1102",
		"description": "Dozent: STF/[Dal]",
		"start": "2025-01-07T08:15:00",
		"end": "2025-01-07T11:30:00"
	},
	{
		"name": "BWI3-SEAP1/01",
		"location": "1102",
		"description": "Dozent: STF/[Dal]",
		"start": "2024-12-03T08:15:00",
		"end": "2024-12-03T11:30:00"
	}
]
