[
	{
		"name": "Praktikum (Praktikum)",
		"location": "S4.01, Ulmenliet 20, Hauptgebäude",
		"description": "Dozent: Prof. Dr. Nina Riedel\nRhythmus: wöchentlich\n\nOriginaler Titel: Praktikum - Einführung",
		"startTime": "2026-04-10T09:15:00",
		"endTime": "2026-04-10T10:00:00"
	},
	{
		"name": "Praktikum (Praktikum)",
		"location": "S4.01, Ulmenliet 20, Hauptgebäude",
		"description": "Dozent: Prof. Dr. Nina Riedel\nRhythmus: wöchentlich\n\nOriginaler Titel: Praktikum - Einführung",
		"startTime": "2026-04-17T09:15:00",
		"endTime": "2026-04-17T10:00:00"
	},
	{
		"name": "Praktikum (Praktikum)",
		"location": "S4.01, Ulmenliet 20, Hauptgebäude",
		"description": "Dozent: Prof. Dr. Nina Riedel\nRhythmus: wöchentlich\n\nOriginaler Titel: Praktikum - Einführung",
		"startTime": "2026-04-24T09:15:00",
		"endTime": "2026-04-24T10:00:00"
	}
]