[
	{
		"name": "M 5.1.5 ((Koh A) TPS Erkundung des Arbeitsfeldes)",
		"location": "2.05, Alexanderstraße 1",
		"description": "Dozent: Rebecca Lier\nParallelgruppe: 5\nMax. Anzahl von Teilnehmer/-innen: 14\nRhythmus: wöchentlich\n\nOriginaler Titel: BABE M 5.1.5 (Koh A) TPS Erkundung des Arbeitsfeldes (5. Parallelgruppe)",
		"startTime": "2025-10-23T15:00:00",
		"endTime": "2025-10-23T17:30:00"
	},
	{
		"name": "M 5.1.5 ((Koh A) TPS Erkundung des Arbeitsfeldes)",
		"location": "2.05, Alexanderstraße 1",
		"description": "Dozent: Rebecca Lier\nParallelgruppe: 5\nMax. Anzahl von Teilnehmer/-innen: 14\nRhythmus: wöchentlich\n\nOriginaler Titel: BABE M 5.1.5 (Koh A) TPS Erkundung des Arbeitsfeldes (5. Parallelgruppe)",
		"startTime": "2025-10-30T15:00:00",
		"endTime": "2025-10-30T17:30:00"
	},
	{
		"name": "M 5.1.5 ((Koh A) TPS Erkundung des Arbeitsfeldes)",
		"location": "2.05, Alexanderstraße 1",
		"description": "Dozent: Rebecca Lier\nParallelgruppe: 5\nMax. Anzahl von Teilnehmer/-innen: 14\nRhythmus: wöchentlich\n\nOriginaler Titel: BABE M 5.1.5 (Koh A) TPS Erkundung des Arbeitsfeldes (5. Parallelgruppe)",
		"startTime": "2025-11-06T15:00:00",
		"endTime": "2025-11-06T17:30:00"
	},
	{
		"name": "M 5.1.5 ((Koh A) TPS Erkundung des Arbeitsfeldes)",
		"location": "2.05, Alexanderstraße 1",
		"description": "Dozent: Rebecca Lier\nParallelgruppe: 5\nMax. Anzahl von Teilnehmer/-innen: 14\nRhythmus: wöchentlich\n\nOriginaler Titel: BABE M 5.1.5 (Koh A) TPS Erkundung des Arbeitsfeldes (5. Parallelgruppe)",
		"startTime": "2025-11-13T15:00:00",
		"endTime": "2025-11-13T17:30:00"
	},
	{
		"name": "M 5.1.5 ((Koh A) TPS Erkundung des Arbeitsfeldes)",
		"location": "2.05, Alexanderstraße 1",
		"description": "Dozent: Rebecca Lier\nParallelgruppe: 5\nMax. Anzahl von Teilnehmer/-innen: 14\nRhythmus: wöchentlich\n\nOriginaler Titel: BABE M 5.1.5 (Koh A) TPS Erkundung des Arbeitsfeldes (5. Parallelgruppe)",
		"startTime": "2025-11-20T15:00:00",
		"endTime": "2025-11-20T17:30:00"
	},
	{
		"name": "M 5.1.5 ((Koh A) TPS Erkundung des Arbeitsfeldes)",
		"location": "2.05, Alexanderstraße 1",
		"description": "Dozent: Rebecca Lier\nParallelgruppe: 5\nMax. Anzahl von Teilnehmer/-innen: 14\nRhythmus: wöchentlich\n\nOriginaler Titel: BABE M 5.1.5 (Koh A) TPS Erkundung des Arbeitsfeldes (5. Parallelgruppe)",
		"startTime": "2025-12-04T15:00:00",
		"endTime": "2025-12-04T17:30:00"
	},
	{
		"name": "M 5.1.5 ((Koh A) TPS Erkundung des Arbeitsfeldes)",
		"location": "2.05, Alexanderstraße 1",
		"description": "Dozent: Rebecca Lier\nParallelgruppe: 5\nMax. Anzahl von Teilnehmer/-innen: 14\nRhythmus: wöchentlich\n\nOriginaler Titel: BABE M 5.1.5 (Koh A) TPS Erkundung des Arbeitsfeldes (5. Parallelgruppe)",
		"startTime": "2025-12-11T15:00:00",
		"endTime": "2025-12-11T17:30:00"
	},
	{
		"name": "M 5.1.5 ((Koh A) TPS Erkundung des Arbeitsfeldes)",
		"location": "2.05, Alexanderstraße 1",
		"description": "Dozent: Rebecca Lier\nParallelgruppe: 5\nMax. Anzahl von Teilnehmer/-innen: 14\nRhythmus: wöchentlich\n\nOriginaler Titel: BABE M 5.1.5 (Koh A) TPS Erkundung des Arbeitsfeldes (5. Parallelgruppe)",
		"startTime": "2025-12-18T15:00:00",
		"endTime": "2025-12-18T17:30:00"
	},
	{
		"name": "M 5.1.5 ((Koh A) TPS Erkundung des Arbeitsfeldes)",
		"location": "2.05, Alexanderstraße 1",
		"description": "Dozent: Rebecca Lier\nParallelgruppe: 5\nMax. Anzahl von Teilnehmer/-innen: 14\nRhythmus: wöchentlich\n\nOriginaler Titel: BABE M 5.1.5 (Koh A) TPS Erkundung des Arbeitsfeldes (5. Parallelgruppe)",
		"startTime": "2026-01-08T15:00:00",
		"endTime": "2026-01-08T17:30:00"
	},
	{
		"name": "M 5.1.5 ((Koh A) TPS Erkundung des Arbeitsfeldes)",
		"location": "2.05, Alexanderstraße 1",
		"description": "Dozent: Rebecca Lier\nParallelgruppe: 5\nMax. Anzahl von Teilnehmer/-innen: 14\nRhythmus: wöchentlich\n\nOriginaler Titel: BABE M 5.1.5 (Koh A) TPS Erkundung des Arbeitsfeldes (5. Parallelgruppe)",
		"startTime": "2026-01-15T15:00:00",
		"endTime": "2026-01-15T17:30:00"
	},
	{
		"name": "M 5.1.5 ((Koh A) TPS Erkundung des Arbeitsfeldes)",
		"location": "2.05, Alexanderstraße 1",
		"description": "Dozent: Rebecca Lier\nParallelgruppe: 5\nMax. Anzahl von Teilnehmer/-innen: 14\nRhythmus: wöchentlich\n\nOriginaler Titel: BABE M 5.1.5 (Koh A) TPS Erkundung des Arbeitsfeldes (5. Parallelgruppe)",
		"startTime": "2026-01-22T15:00:00",
		"endTime": "2026-01-22T17:30:00"
	},
	{
		"name": "M 5.1.5 ((Koh A) TPS Erkundung des Arbeitsfeldes)",
		"location": "2.05, Alexanderstraße 1",
		"description": "Dozent: Rebecca Lier\nParallelgruppe: 5\nMax. Anzahl von Teilnehmer/-innen: 14\nRhythmus: wöchentlich\n\nOriginaler Titel: BABE M 5.1.5 (Koh A) TPS Erkundung des Arbeitsfeldes (5. Parallelgruppe)",
		"startTime": "2026-01-29T15:00:00",
		"endTime": "2026-01-29T17:30:00"
	}
]