[
	{
		"name": "Gend & Migra LV/01 (Gender und Migration)",
		"location": "2.05, Alexanderstraße 1",
		"description": "Dozent: Prof. Dr. Carmen Gransee\nParallelgruppe: 1\nMax. Anzahl von Teilnehmer/-innen: 20\nRhythmus: Einzeltermin\n\nOriginaler Titel: BASA M16.1.1 & M16.2.1 Gender und Migration (1. Parallelgruppe)",
		"startTime": "2026-04-16T10:00:00",
		"endTime": "2026-04-16T18:45:00"
	},
	{
		"name": "Gend & Migra LV/01 (Gender und Migration)",
		"location": "2.05, Alexanderstraße 1",
		"description": "Dozent: Prof. Dr. Carmen Gransee\nParallelgruppe: 1\nMax. Anzahl von Teilnehmer/-innen: 20\nRhythmus: Einzeltermin\n\nOriginaler Titel: BASA M16.1.1 & M16.2.1 Gender und Migration (1. Parallelgruppe)",
		"startTime": "2026-04-17T10:00:00",
		"endTime": "2026-04-17T18:45:00"
	},
	{
		"name": "Gend & Migra LV/01 (Gender und Migration)",
		"location": "2.05, Alexanderstraße 1",
		"description": "Dozent: Prof. Dr. Carmen Gransee\nParallelgruppe: 1\nMax. Anzahl von Teilnehmer/-innen: 20\nRhythmus: Einzeltermin\n\nOriginaler Titel: BASA M16.1.1 & M16.2.1 Gender und Migration (1. Parallelgruppe)",
		"startTime": "2026-04-18T10:00:00",
		"endTime": "2026-04-18T18:00:00"
	},
	{
		"name": "Gend & Migra LV/01 (Gender und Migration)",
		"location": "2.05, Alexanderstraße 1",
		"description": "Dozent: Prof. Dr. Carmen Gransee\nParallelgruppe: 1\nMax. Anzahl von Teilnehmer/-innen: 20\nRhythmus: Einzeltermin\n\nOriginaler Titel: BASA M16.1.1 & M16.2.1 Gender und Migration (1. Parallelgruppe)",
		"startTime": "2026-05-15T14:30:00",
		"endTime": "2026-05-15T17:45:00"
	},
	{
		"name": "Gend & Migra LV/01 (Gender und Migration)",
		"location": "2.05, Alexanderstraße 1",
		"description": "Dozent: Prof. Dr. Carmen Gransee\nParallelgruppe: 1\nMax. Anzahl von Teilnehmer/-innen: 20\nRhythmus: Einzeltermin\n\nOriginaler Titel: BASA M16.1.1 & M16.2.1 Gender und Migration (1. Parallelgruppe)",
		"startTime": "2026-05-16T10:00:00",
		"endTime": "2026-05-16T18:00:00"
	},
	{
		"name": "Gend & Migra LV/01 (Gender und Migration)",
		"location": "2.05, Alexanderstraße 1",
		"description": "Dozent: Prof. Dr. Carmen Gransee\nParallelgruppe: 1\nMax. Anzahl von Teilnehmer/-innen: 20\nRhythmus: Einzeltermin\n\nOriginaler Titel: BASA M16.1.1 & M16.2.1 Gender und Migration (1. Parallelgruppe)",
		"startTime": "2026-05-30T10:00:00",
		"endTime": "2026-05-30T18:00:00"
	}
]