[
	{
		"name": "SE LV (Software Engineering)",
		"location": "(kein Raum angegeben)",
		"description": "Dozent: Fin Engelbart\nMax. Anzahl von Teilnehmer/-innen: 30\nRhythmus: wöchentlich\n\nOriginaler Titel: Software Engineering ^ (1MI-SE.LV)",
		"startTime": "2026-04-13T12:45:00",
		"endTime": "2026-04-13T16:00:00"
	},
	{
		"name": "SE LV (Software Engineering)",
		"location": "(kein Raum angegeben)",
		"description": "Dozent: Fin Engelbart\nMax. Anzahl von Teilnehmer/-innen: 30\nRhythmus: wöchentlich\n\nOriginaler Titel: Software Engineering ^ (1MI-SE.LV)",
		"startTime": "2026-04-20T12:45:00",
		"endTime": "2026-04-20T16:00:00"
	},
	{
		"name": "SE LV (Software Engineering)",
		"location": "(kein Raum angegeben)",
		"description": "Dozent: Fin Engelbart\nMax. Anzahl von Teilnehmer/-innen: 30\nRhythmus: wöchentlich\n\nOriginaler Titel: Software Engineering ^ (1MI-SE.LV)",
		"startTime": "2026-05-04T12:45:00",
		"endTime": "2026-05-04T16:00:00"
	},
	{
		"name": "SE LV (Software Engineering)",
		"location": "(kein Raum angegeben)",
		"description": "Dozent: Fin Engelbart\nMax. Anzahl von Teilnehmer/-innen: 30\nRhythmus: wöchentlich\n\nOriginaler Titel: Software Engineering ^ (1MI-SE.LV)",
		"startTime": "2026-05-11T12:45:00",
		"endTime": "2026-05-11T16:00:00"
	},
	{
		"name": "SE LV (Software Engineering)",
		"location": "(kein Raum angegeben)",
		"description": "Dozent: Fin Engelbart\nMax. Anzahl von Teilnehmer/-innen: 30\nRhythmus: wöchentlich\n\nOriginaler Titel: Software Engineering ^ (1MI-SE.LV)",
		"startTime": "2026-05-18T12:45:00",
		"endTime": "2026-05-18T16:00:00"
	},
	{
		"name": "SE LV (Software Engineering)",
		"location": "(kein Raum angegeben)",
		"description": "Dozent: Fin Engelbart\nMax. Anzahl von Teilnehmer/-innen: 30\nRhythmus: wöchentlich\n\nOriginaler Titel: Software Engineering ^ (1MI-SE.LV)",
		"startTime": "2026-06-01T12:45:00",
		"endTime": "2026-06-01T16:00:00"
	},
	{
		"name": "SE LV (Software Engineering)",
		"location": "(kein Raum angegeben)",
		"description": "Dozent: Fin Engelbart\nMax. Anzahl von Teilnehmer/-innen: 30\nRhythmus: wöchentlich\n\nOriginaler Titel: Software Engineering ^ (1MI-SE.LV)",
		"startTime": "2026-06-08T12:45:00",
		"endTime": "2026-06-08T16:00:00"
	},
	{
		"name": "SE LV (Software Engineering)",
		"location": "(kein Raum angegeben)",
		"description": "Dozent: Fin Engelbart\nMax. Anzahl von Teilnehmer/-innen: 30\nRhythmus: wöchentlich\n\nOriginaler Titel: Software Engineering ^ (1MI-SE.LV)",
		"startTime": "2026-06-15T12:45:00",
		"endTime": "2026-06-15T16:00:00"
	},
	{
		"name": "SE LV (Software Engineering)",
		"location": "(kein Raum angegeben)",
		"description": "Dozent: Fin Engelbart\nMax. Anzahl von Teilnehmer/-innen: 30\nRhythmus: wöchentlich\n\nOriginaler Titel: Software Engineering ^ (1MI-SE.LV)",
		"startTime": "2026-06-22T12:45:00",
		"endTime": "2026-06-22T16:00:00"
	},
	{
		"name": "SE LV (Software Engineering)",
		"location": "(kein Raum angegeben)",
		"description": "Dozent: Fin Engelbart\nMax. Anzahl von Teilnehmer/-innen: 30\nRhythmus: wöchentlich\n\nOriginaler Titel: Software Engineering ^ (1MI-SE.LV)",
		"startTime": "2026-06-29T12:45:00",
		"endTime": "2026-06-29T16:00:00"
	},
	{
		"name": "SE LV (Software Engineering)",
		"location": "(kein Raum angegeben)",
		"description": "Dozent: Fin Engelbart\nMax. Anzahl von Teilnehmer/-innen: 30\nRhythmus: wöchentlich\n\nOriginaler Titel: Software Engineering ^ (1MI-SE.LV)",
		"startTime": "2026-07-06T12:45:00",
		"endTime": "2026-07-06T16:00:00"
	},
	{
		"name": "SE LV (Software Engineering)",
		"location": "(kein Raum angegeben)",
		"description": "Dozent: Fin Engelbart\nMax. Anzahl von Teilnehmer/-innen: 30\nRhythmus: wöchentlich\n\nOriginaler Titel: Software Engineering ^ (1MI-SE.LV)",
		"startTime": "2026-07-13T12:45:00",
		"endTime": "2026-07-13T16:00:00"
	},
	{
		"name": "SE LV (Software Engineering)",
		"location": "(kein Raum angegeben)",
		"description": "Dozent: Fin Engelbart\nMax. Anzahl von Teilnehmer/-innen: 30\nRhythmus: wöchentlich\n\nOriginaler Titel: Software Engineering ^ (1MI-SE.LV)",
		"startTime": "2026-07-20T12:45:00",
		"endTime": "2026-07-20T16:00:00"
	}
]